odoo/addons/website_geoengine/README.rst
odoo/addons/website_geoengine/__init__.py
odoo/addons/website_geoengine/__manifest__.py
odoo/addons/website_geoengine/controllers/__init__.py
odoo/addons/website_geoengine/controllers/res_partner.py
odoo/addons/website_geoengine/i18n/it.po
odoo/addons/website_geoengine/i18n/website_geoengine.pot
odoo/addons/website_geoengine/models/__init__.py
odoo/addons/website_geoengine/models/res_partner.py
odoo/addons/website_geoengine/readme/CONFIGURE.rst
odoo/addons/website_geoengine/readme/CONTRIBUTORS.rst
odoo/addons/website_geoengine/readme/DESCRIPTION.rst
odoo/addons/website_geoengine/readme/USAGE.rst
odoo/addons/website_geoengine/static/description/icon.png
odoo/addons/website_geoengine/static/description/index.html
odoo_addon_website_geoengine-16.0.1.0.0.4.dist-info/METADATA
odoo_addon_website_geoengine-16.0.1.0.0.4.dist-info/WHEEL
odoo_addon_website_geoengine-16.0.1.0.0.4.dist-info/top_level.txt
odoo_addon_website_geoengine-16.0.1.0.0.4.dist-info/RECORD
